[
  {
    "iri": "http://example.org/building/storey_1",
    "label": "Storey 1",
    "serialization": {
      "rotation": 1.6,
      "location": "14.680497699036852,3.6991820842035597,0.0",
      "size": "9.149052421168253,11.390705476647625,3.4040171419700727"
    },
    "intersects": [],
    "isAbove": [],
    "isBelow": [],
    "adjacency": []
  },
  {
    "iri": "http://example.org/building/building",
    "label": "Building",
    "serialization": {
      "rotation": 3.1,
      "location": "14.416291763588081,12.855749256864218,0.0",
      "size": "11.32999074221747,9.900136394380311,8.47078830800766"
    },
    "intersects": [],
    "isAbove": [],
    "isBelow": [],
    "adjacency": []
  },
  {
    "iri": "http://example.org/building/storey_1_column_3",
    "label": "Column",
    "serialization": {
      "rotation": 3.8000000000000003,
      "location": "9.138722834735068,6.3731079536828,0.17001425673842985",
      "size": "0.5657509507146603,0.665859838010351,3.234002885231643"
    },
    "intersects": [],
    "isAbove": [],
    "isBelow": [
      "http://example.org/building/storey_2_column_1",
      "http://example.org/building/storey_2_wall_1"
    ],
    "adjacency": [
      "http://example.org/building/floor_slab",
      "http://example.org/building/slab_1"
    ]
  },
  {
    "iri": "http://example.org/building/slab_1",
    "label": "Slab 1",
    "serialization": {
      "rotation": 1.6,
      "location": "14.162604308394364,3.968061291731206,3.404017141970072",
      "size": "8.865165623307146,10.369149332574105,0.17001425673842974"
    },
    "intersects": [
      "http://example.org/building/storey_1_column_1",
      "http://example.org/building/storey_1_column_2",
      "http://example.org/building/storey_1_column_3",
      "http://example.org/building/storey_1_column_4",
      "http://example.org/building/storey_2_column_1",
      "http://example.org/building/storey_1_wall_1",
      "http://example.org/building/storey_2_wall_1"
    ],
    "isAbove": [],
    "isBelow": [],
    "adjacency": []
  },
  {
    "iri": "http://example.org/building/storey_1_column_1",
    "label": "Column",
    "serialization": {
      "rotation": 3.9000000000000004,
      "location": "11.668666366498622,5.769268180849133,0.1700142567384299",
      "size": "0.5343105516102824,0.5189783563863948,3.234002885231643"
    },
    "intersects": [
      "http://example.org/building/storey_1_column_4"
    ],
    "isAbove": [],
    "isBelow": [
      "http://example.org/building/storey_2_column_1",
      "http://example.org/building/storey_2_wall_1"
    ],
    "adjacency": [
      "http://example.org/building/floor_slab",
      "http://example.org/building/slab_1"
    ]
  },
  {
    "iri": "http://example.org/building/storey_2_wall_1",
    "label": "Wall",
    "serialization": {
      "rotation": 4.0,
      "location": "5.1322759661585575,8.635536368354131,3.574031398708502",
      "size": "0.30686074668605023,2.1975935296756757,4.896756909299155"
    },
    "intersects": [],
    "isAbove": [
      "http://example.org/building/storey_1_column_1",
      "http://example.org/building/storey_1_column_2",
      "http://example.org/building/storey_1_column_3",
      "http://example.org/building/storey_1_column_4",
      "http://example.org/building/storey_1_wall_1"
    ],
    "isBelow": [],
    "adjacency": [
      "http://example.org/building/slab_1",
      "http://example.org/building/roof_slab"
    ]
  },
  {
    "iri": "http://example.org/building/floor_slab",
    "label": "Floor Slab",
    "serialization": {
      "rotation": 3.2,
      "location": "14.414367180795363,12.809503761836305,0.0",
      "size": "11.399132413925482,9.043135363407647,0.17001425673842993"
    },
    "intersects": [
      "http://example.org/building/storey_1_column_1",
      "http://example.org/building/storey_1_column_2",
      "http://example.org/building/storey_1_column_3",
      "http://example.org/building/storey_1_column_4",
      "http://example.org/building/storey_1_wall_1"
    ],
    "isAbove": [],
    "isBelow": [
      "http://example.org/building/storey_2_column_1",
      "http://example.org/building/storey_2_wall_1"
    ],
    "adjacency": []
  },
  {
    "iri": "http://example.org/building/roof_slab",
    "label": "Roof Slab",
    "serialization": {
      "rotation": 1.6,
      "location": "13.867114766771389,4.310833016214674,8.47078830800766",
      "size": "9.24293381097246,9.344233914958899,0.17001425673842974"
    },
    "intersects": [
      "http://example.org/building/storey_2_column_1",
      "http://example.org/building/storey_2_wall_1"
    ],
    "isAbove": [
      "http://example.org/building/storey_1_column_1",
      "http://example.org/building/storey_1_column_2",
      "http://example.org/building/storey_1_column_3",
      "http://example.org/building/storey_1_column_4",
      "http://example.org/building/storey_1_wall_1"
    ],
    "isBelow": [],
    "adjacency": []
  },
  {
    "iri": "http://example.org/building/storey_2_column_1",
    "label": "Column",
    "serialization": {
      "rotation": 4.2,
      "location": "6.462535963099599,10.934600484628653,3.5740313987085006",
      "size": "0.8610846599170063,0.565528271871637,4.896756909299155"
    },
    "intersects": [],
    "isAbove": [
      "http://example.org/building/storey_1_column_1",
      "http://example.org/building/storey_1_column_2",
      "http://example.org/building/storey_1_column_3",
      "http://example.org/building/storey_1_column_4",
      "http://example.org/building/storey_1_wall_1"
    ],
    "isBelow": [],
    "adjacency": [
      "http://example.org/building/slab_1",
      "http://example.org/building/roof_slab"
    ]
  },
  {
    "iri": "http://example.org/building/storey_2",
    "label": "Storey 2",
    "serialization": {
      "rotation": 1.6,
      "location": "14.162604308394364,3.9680612917312055,3.404017141970072",
      "size": "9.594187532095567,10.369149332574105,5.0667711660375865"
    },
    "intersects": [],
    "isAbove": [],
    "isBelow": [],
    "adjacency": []
  },
  {
    "iri": "http://example.org/building/storey_1_column_2",
    "label": "Column",
    "serialization": {
      "rotation": 5.4,
      "location": "6.945159644529891,10.033632341340152,0.17001425673842985",
      "size": "0.7923219315654815,0.7036987713472129,3.234002885231643"
    },
    "intersects": [
      "http://example.org/building/storey_1_wall_1"
    ],
    "isAbove": [],
    "isBelow": [
      "http://example.org/building/storey_2_column_1",
      "http://example.org/building/storey_2_wall_1"
    ],
    "adjacency": [
      "http://example.org/building/floor_slab",
      "http://example.org/building/slab_1"
    ]
  },
  {
    "iri": "http://example.org/building/storey_1_column_4",
    "label": "Column",
    "serialization": {
      "rotation": 5.7,
      "location": "11.274859658970794,5.511760082017849,0.1700142567384299",
      "size": "0.6674506907423723,0.8921722023315084,3.234002885231643"
    },
    "intersects": [
      "http://example.org/building/storey_1_column_1"
    ],
    "isAbove": [],
    "isBelow": [
      "http://example.org/building/storey_2_column_1",
      "http://example.org/building/storey_2_wall_1"
    ],
    "adjacency": [
      "http://example.org/building/floor_slab",
      "http://example.org/building/slab_1"
    ]
  },
  {
    "iri": "http://example.org/building/storey_1_wall_1",
    "label": "Wall",
    "serialization": {
      "rotation": 6.1000000000000005,
      "location": "6.241827448151671,9.758762435874875,0.17001425673842993",
      "size": "6.673137204925715,0.22099253385204598,3.234002885231643"
    },
    "intersects": [
      "http://example.org/building/storey_1_column_2"
    ],
    "isAbove": [],
    "isBelow": [
      "http://example.org/building/storey_2_column_1",
      "http://example.org/building/storey_2_wall_1"
    ],
    "adjacency": [
      "http://example.org/building/floor_slab",
      "http://example.org/building/slab_1"
    ]
  }
]