[
  {
    "iri": "http://example.org/building/storey_1_column_1",
    "label": "Column",
    "serialization": {
      "rotation": 0.0,
      "location": "5.7646395016110565,14.597860615235629,0.30834983418219825",
      "size": "0.5549290169215828,0.38397953810864216,3.7240070895003616"
    },
    "intersects": [],
    "isAbove": [],
    "isBelow": [
      "http://example.org/building/storey_2_column_1",
      "http://example.org/building/storey_3_column_1",
      "http://example.org/building/storey_4_column_1",
      "http://example.org/building/storey_4_column_2",
      "http://example.org/building/storey_4_column_3",
      "http://example.org/building/storey_2_wall_1",
      "http://example.org/building/storey_2_wall_2",
      "http://example.org/building/storey_3_wall_1",
      "http://example.org/building/storey_3_wall_2",
      "http://example.org/building/storey_4_wall_1"
    ],
    "adjacency": [
      "http://example.org/building/floor_slab",
      "http://example.org/building/slab_1"
    ]
  },
  {
    "iri": "http://example.org/building/storey_1_wall_3",
    "label": "Wall",
    "serialization": {
      "rotation": 3.3000000000000003,
      "location": "-8.628607503894367,-11.945895395027,0.30834983418219825",
      "size": "0.36557470479637466,2.9657297144225776,3.7240070895003616"
    },
    "intersects": [],
    "isAbove": [],
    "isBelow": [
      "http://example.org/building/storey_2_column_1",
      "http://example.org/building/storey_3_column_1",
      "http://example.org/building/storey_4_column_1",
      "http://example.org/building/storey_4_column_2",
      "http://example.org/building/storey_4_column_3",
      "http://example.org/building/storey_2_wall_1",
      "http://example.org/building/storey_2_wall_2",
      "http://example.org/building/storey_3_wall_1",
      "http://example.org/building/storey_3_wall_2",
      "http://example.org/building/storey_4_wall_1"
    ],
    "adjacency": [
      "http://example.org/building/floor_slab",
      "http://example.org/building/slab_1"
    ]
  },
  {
    "iri": "http://example.org/building/storey_3",
    "label": "Storey 3",
    "serialization": {
      "rotation": 0.0,
      "location": "3.2492127635518533,4.03682796125772,7.58271968953607",
      "size": "7.3780582606932,12.532902901391687,3.4399894984779937"
    },
    "intersects": [],
    "isAbove": [],
    "isBelow": [],
    "adjacency": []
  },
  {
    "iri": "http://example.org/building/storey_3_column_1",
    "label": "Column",
    "serialization": {
      "rotation": 0.0,
      "location": "6.977457514588622,9.239240319166147,7.891069523718269",
      "size": "0.6442574455728778,0.45585818251572263,3.1316396642957915"
    },
    "intersects": [],
    "isAbove": [
      "http://example.org/building/storey_1_column_1",
      "http://example.org/building/storey_1_column_2",
      "http://example.org/building/storey_2_column_1",
      "http://example.org/building/storey_1_wall_1",
      "http://example.org/building/storey_1_wall_2",
      "http://example.org/building/storey_1_wall_3",
      "http://example.org/building/storey_2_wall_1",
      "http://example.org/building/storey_2_wall_2"
    ],
    "isBelow": [
      "http://example.org/building/storey_4_column_1",
      "http://example.org/building/storey_4_column_2",
      "http://example.org/building/storey_4_column_3",
      "http://example.org/building/storey_4_wall_1"
    ],
    "adjacency": [
      "http://example.org/building/slab_2",
      "http://example.org/building/slab_3"
    ]
  },
  {
    "iri": "http://example.org/building/building",
    "label": "Building",
    "serialization": {
      "rotation": 4.7,
      "location": "-18.03693291544266,3.0033834767567558,0.0",
      "size": "14.169249873377753,7.583924253996116,13.885119082515127"
    },
    "intersects": [],
    "isAbove": [],
    "isBelow": [],
    "adjacency": []
  },
  {
    "iri": "http://example.org/building/storey_3_wall_1",
    "label": "Wall",
    "serialization": {
      "rotation": 2.3000000000000003,
      "location": "3.1205089908390966,-15.382272198293295,7.891069523718269",
      "size": "0.3396191877787369,4.874120032331701,3.1316396642957933"
    },
    "intersects": [],
    "isAbove": [
      "http://example.org/building/storey_1_column_1",
      "http://example.org/building/storey_1_column_2",
      "http://example.org/building/storey_2_column_1",
      "http://example.org/building/storey_1_wall_1",
      "http://example.org/building/storey_1_wall_2",
      "http://example.org/building/storey_1_wall_3",
      "http://example.org/building/storey_2_wall_1",
      "http://example.org/building/storey_2_wall_2"
    ],
    "isBelow": [
      "http://example.org/building/storey_4_column_1",
      "http://example.org/building/storey_4_column_2",
      "http://example.org/building/storey_4_column_3",
      "http://example.org/building/storey_4_wall_1"
    ],
    "adjacency": [
      "http://example.org/building/slab_2",
      "http://example.org/building/slab_3"
    ]
  },
  {
    "iri": "http://example.org/building/storey_4_wall_1",
    "label": "Wall",
    "serialization": {
      "rotation": 5.9,
      "location": "1.3848566915303255,8.991247386504432,11.331059022196259",
      "size": "0.35789286485854355,4.766366465965401,2.554060060318866"
    },
    "intersects": [],
    "isAbove": [
      "http://example.org/building/storey_1_column_1",
      "http://example.org/building/storey_1_column_2",
      "http://example.org/building/storey_2_column_1",
      "http://example.org/building/storey_3_column_1",
      "http://example.org/building/storey_1_wall_1",
      "http://example.org/building/storey_1_wall_2",
      "http://example.org/building/storey_1_wall_3",
      "http://example.org/building/storey_2_wall_1",
      "http://example.org/building/storey_2_wall_2",
      "http://example.org/building/storey_3_wall_1",
      "http://example.org/building/storey_3_wall_2"
    ],
    "isBelow": [],
    "adjacency": [
      "http://example.org/building/slab_3",
      "http://example.org/building/roof_slab"
    ]
  },
  {
    "iri": "http://example.org/building/storey_2",
    "label": "Storey 2",
    "serialization": {
      "rotation": 0.0,
      "location": "3.4855075319737,4.241146104290089,4.03235692368256",
      "size": "7.153557614378319,12.954232502297014,3.550362765853512"
    },
    "intersects": [],
    "isAbove": [],
    "isBelow": [],
    "adjacency": []
  },
  {
    "iri": "http://example.org/building/storey_4",
    "label": "Storey 4",
    "serialization": {
      "rotation": 3.1,
      "location": "-10.441792775066153,-16.38805898969286,11.02270918801406",
      "size": "7.556216056248251,12.311377260211021,2.8624098945010665"
    },
    "intersects": [],
    "isAbove": [],
    "isBelow": [],
    "adjacency": []
  },
  {
    "iri": "http://example.org/building/roof_slab",
    "label": "Roof Slab",
    "serialization": {
      "rotation": 3.1,
      "location": "-10.441792775066155,-16.037997407390364,13.885119082515127",
      "size": "7.556216056248253,11.961315677908527,0.30834983418219863"
    },
    "intersects": [
      "http://example.org/building/storey_4_column_1",
      "http://example.org/building/storey_4_column_2",
      "http://example.org/building/storey_4_column_3",
      "http://example.org/building/storey_4_wall_1"
    ],
    "isAbove": [
      "http://example.org/building/storey_1_column_1",
      "http://example.org/building/storey_1_column_2",
      "http://example.org/building/storey_2_column_1",
      "http://example.org/building/storey_3_column_1",
      "http://example.org/building/storey_1_wall_1",
      "http://example.org/building/storey_1_wall_2",
      "http://example.org/building/storey_1_wall_3",
      "http://example.org/building/storey_2_wall_1",
      "http://example.org/building/storey_2_wall_2",
      "http://example.org/building/storey_3_wall_1",
      "http://example.org/building/storey_3_wall_2"
    ],
    "isBelow": [],
    "adjacency": []
  },
  {
    "iri": "http://example.org/building/storey_4_column_3",
    "label": "Column",
    "serialization": {
      "rotation": 4.0,
      "location": "-9.763987122546304,1.8072790623332393,11.331059022196253",
      "size": "0.6122087143971378,0.5617178922885842,2.5540600603188715"
    },
    "intersects": [],
    "isAbove": [
      "http://example.org/building/storey_1_column_1",
      "http://example.org/building/storey_1_column_2",
      "http://example.org/building/storey_2_column_1",
      "http://example.org/building/storey_3_column_1",
      "http://example.org/building/storey_1_wall_1",
      "http://example.org/building/storey_1_wall_2",
      "http://example.org/building/storey_1_wall_3",
      "http://example.org/building/storey_2_wall_1",
      "http://example.org/building/storey_2_wall_2",
      "http://example.org/building/storey_3_wall_1",
      "http://example.org/building/storey_3_wall_2"
    ],
    "isBelow": [],
    "adjacency": [
      "http://example.org/building/slab_3",
      "http://example.org/building/roof_slab"
    ]
  },
  {
    "iri": "http://example.org/building/storey_1_wall_2",
    "label": "Wall",
    "serialization": {
      "rotation": 2.2,
      "location": "4.70272246840278,-15.058679155174822,0.30834983418219825",
      "size": "2.787948462372432,0.17323174040334877,3.7240070895003625"
    },
    "intersects": [],
    "isAbove": [],
    "isBelow": [
      "http://example.org/building/storey_2_column_1",
      "http://example.org/building/storey_3_column_1",
      "http://example.org/building/storey_4_column_1",
      "http://example.org/building/storey_4_column_2",
      "http://example.org/building/storey_4_column_3",
      "http://example.org/building/storey_2_wall_1",
      "http://example.org/building/storey_2_wall_2",
      "http://example.org/building/storey_3_wall_1",
      "http://example.org/building/storey_3_wall_2",
      "http://example.org/building/storey_4_wall_1"
    ],
    "adjacency": [
      "http://example.org/building/floor_slab",
      "http://example.org/building/slab_1"
    ]
  },
  {
    "iri": "http://example.org/building/storey_1",
    "label": "Storey 1",
    "serialization": {
      "rotation": 0.0,
      "location": "3.7293839007655474,4.403372124795577,0.0",
      "size": "6.953230863688228,13.502591618701352,4.032356923682562"
    },
    "intersects": [],
    "isAbove": [],
    "isBelow": [],
    "adjacency": []
  },
  {
    "iri": "http://example.org/building/storey_2_wall_1",
    "label": "Wall",
    "serialization": {
      "rotation": 1.7000000000000002,
      "location": "6.179827255847982,-10.103566791416048,4.340706757864759",
      "size": "7.0041744218235795,0.33874199706518127,3.2420129316713107"
    },
    "intersects": [],
    "isAbove": [
      "http://example.org/building/storey_1_column_1",
      "http://example.org/building/storey_1_column_2",
      "http://example.org/building/storey_1_wall_1",
      "http://example.org/building/storey_1_wall_2",
      "http://example.org/building/storey_1_wall_3"
    ],
    "isBelow": [
      "http://example.org/building/storey_3_column_1",
      "http://example.org/building/storey_4_column_1",
      "http://example.org/building/storey_4_column_2",
      "http://example.org/building/storey_4_column_3",
      "http://example.org/building/storey_3_wall_1",
      "http://example.org/building/storey_3_wall_2",
      "http://example.org/building/storey_4_wall_1"
    ],
    "adjacency": [
      "http://example.org/building/slab_1",
      "http://example.org/building/slab_2"
    ]
  },
  {
    "iri": "http://example.org/building/storey_4_column_1",
    "label": "Column",
    "serialization": {
      "rotation": 3.7,
      "location": "-12.951313607974992,-9.366022261530613,11.331059022196253",
      "size": "0.8774372502673806,0.6256085641189344,2.5540600603188715"
    },
    "intersects": [],
    "isAbove": [
      "http://example.org/building/storey_1_column_1",
      "http://example.org/building/storey_1_column_2",
      "http://example.org/building/storey_2_column_1",
      "http://example.org/building/storey_3_column_1",
      "http://example.org/building/storey_1_wall_1",
      "http://example.org/building/storey_1_wall_2",
      "http://example.org/building/storey_1_wall_3",
      "http://example.org/building/storey_2_wall_1",
      "http://example.org/building/storey_2_wall_2",
      "http://example.org/building/storey_3_wall_1",
      "http://example.org/building/storey_3_wall_2"
    ],
    "isBelow": [],
    "adjacency": [
      "http://example.org/building/slab_3",
      "http://example.org/building/roof_slab"
    ]
  },
  {
    "iri": "http://example.org/building/storey_2_wall_2",
    "label": "Wall",
    "serialization": {
      "rotation": 2.6,
      "location": "0.2771294398786699,-16.065647318718554,4.340706757864759",
      "size": "0.3335556502929249,3.7392331646238404,3.2420129316713115"
    },
    "intersects": [],
    "isAbove": [
      "http://example.org/building/storey_1_column_1",
      "http://example.org/building/storey_1_column_2",
      "http://example.org/building/storey_1_wall_1",
      "http://example.org/building/storey_1_wall_2",
      "http://example.org/building/storey_1_wall_3"
    ],
    "isBelow": [
      "http://example.org/building/storey_3_column_1",
      "http://example.org/building/storey_4_column_1",
      "http://example.org/building/storey_4_column_2",
      "http://example.org/building/storey_4_column_3",
      "http://example.org/building/storey_3_wall_1",
      "http://example.org/building/storey_3_wall_2",
      "http://example.org/building/storey_4_wall_1"
    ],
    "adjacency": [
      "http://example.org/building/slab_1",
      "http://example.org/building/slab_2"
    ]
  },
  {
    "iri": "http://example.org/building/slab_3",
    "label": "Slab 3",
    "serialization": {
      "rotation": 4.7,
      "location": "-16.23686695532048,3.1983685635418886,11.02270918801406",
      "size": "12.112963617606114,7.366649404138045,0.3083498341822004"
    },
    "intersects": [
      "http://example.org/building/storey_3_column_1",
      "http://example.org/building/storey_4_column_1",
      "http://example.org/building/storey_4_column_2",
      "http://example.org/building/storey_4_column_3",
      "http://example.org/building/storey_3_wall_1",
      "http://example.org/building/storey_3_wall_2",
      "http://example.org/building/storey_4_wall_1"
    ],
    "isAbove": [
      "http://example.org/building/storey_1_column_1",
      "http://example.org/building/storey_1_column_2",
      "http://example.org/building/storey_2_column_1",
      "http://example.org/building/storey_1_wall_1",
      "http://example.org/building/storey_1_wall_2",
      "http://example.org/building/storey_1_wall_3",
      "http://example.org/building/storey_2_wall_1",
      "http://example.org/building/storey_2_wall_2"
    ],
    "isBelow": [],
    "adjacency": []
  },
  {
    "iri": "http://example.org/building/storey_4_column_2",
    "label": "Column",
    "serialization": {
      "rotation": 0.8,
      "location": "11.890856364364335,1.3768785305868834,11.331059022196253",
      "size": "0.8278927269685497,0.8404958202085862,2.554060060318875"
    },
    "intersects": [],
    "isAbove": [
      "http://example.org/building/storey_1_column_1",
      "http://example.org/building/storey_1_column_2",
      "http://example.org/building/storey_2_column_1",
      "http://example.org/building/storey_3_column_1",
      "http://example.org/building/storey_1_wall_1",
      "http://example.org/building/storey_1_wall_2",
      "http://example.org/building/storey_1_wall_3",
      "http://example.org/building/storey_2_wall_1",
      "http://example.org/building/storey_2_wall_2",
      "http://example.org/building/storey_3_wall_1",
      "http://example.org/building/storey_3_wall_2"
    ],
    "isBelow": [],
    "adjacency": [
      "http://example.org/building/slab_3",
      "http://example.org/building/roof_slab"
    ]
  },
  {
    "iri": "http://example.org/building/storey_1_wall_1",
    "label": "Wall",
    "serialization": {
      "rotation": 4.6000000000000005,
      "location": "-13.059691192795883,3.9922373885758127,0.30834983418219825",
      "size": "0.9036431376099383,0.3231298852883162,3.7240070895003616"
    },
    "intersects": [],
    "isAbove": [],
    "isBelow": [
      "http://example.org/building/storey_2_column_1",
      "http://example.org/building/storey_3_column_1",
      "http://example.org/building/storey_4_column_1",
      "http://example.org/building/storey_4_column_2",
      "http://example.org/building/storey_4_column_3",
      "http://example.org/building/storey_2_wall_1",
      "http://example.org/building/storey_2_wall_2",
      "http://example.org/building/storey_3_wall_1",
      "http://example.org/building/storey_3_wall_2",
      "http://example.org/building/storey_4_wall_1"
    ],
    "adjacency": [
      "http://example.org/building/floor_slab",
      "http://example.org/building/slab_1"
    ]
  },
  {
    "iri": "http://example.org/building/storey_3_wall_2",
    "label": "Wall",
    "serialization": {
      "rotation": 0.7000000000000001,
      "location": "13.18137522702969,6.937452308038798,7.891069523718269",
      "size": "0.6008580117062792,0.20080610819286004,3.1316396642957933"
    },
    "intersects": [],
    "isAbove": [
      "http://example.org/building/storey_1_column_1",
      "http://example.org/building/storey_1_column_2",
      "http://example.org/building/storey_2_column_1",
      "http://example.org/building/storey_1_wall_1",
      "http://example.org/building/storey_1_wall_2",
      "http://example.org/building/storey_1_wall_3",
      "http://example.org/building/storey_2_wall_1",
      "http://example.org/building/storey_2_wall_2"
    ],
    "isBelow": [
      "http://example.org/building/storey_4_column_1",
      "http://example.org/building/storey_4_column_2",
      "http://example.org/building/storey_4_column_3",
      "http://example.org/building/storey_4_wall_1"
    ],
    "adjacency": [
      "http://example.org/building/slab_2",
      "http://example.org/building/slab_3"
    ]
  },
  {
    "iri": "http://example.org/building/slab_2",
    "label": "Slab 2",
    "serialization": {
      "rotation": 0.0,
      "location": "3.4855075319737,4.241146104290089,7.58271968953607",
      "size": "7.141763492271351,12.328584758359323,0.30834983418219863"
    },
    "intersects": [
      "http://example.org/building/storey_2_column_1",
      "http://example.org/building/storey_3_column_1",
      "http://example.org/building/storey_2_wall_1",
      "http://example.org/building/storey_2_wall_2",
      "http://example.org/building/storey_3_wall_1",
      "http://example.org/building/storey_3_wall_2"
    ],
    "isAbove": [
      "http://example.org/building/storey_1_column_1",
      "http://example.org/building/storey_1_column_2",
      "http://example.org/building/storey_1_wall_1",
      "http://example.org/building/storey_1_wall_2",
      "http://example.org/building/storey_1_wall_3"
    ],
    "isBelow": [
      "http://example.org/building/storey_4_column_1",
      "http://example.org/building/storey_4_column_2",
      "http://example.org/building/storey_4_column_3",
      "http://example.org/building/storey_4_wall_1"
    ],
    "adjacency": []
  },
  {
    "iri": "http://example.org/building/storey_1_column_2",
    "label": "Column",
    "serialization": {
      "rotation": 2.3000000000000003,
      "location": "4.5895042648339555,-16.48494940454878,0.3083498341821982",
      "size": "0.5765776317733495,0.6148079074012784,3.7240070895003616"
    },
    "intersects": [],
    "isAbove": [],
    "isBelow": [
      "http://example.org/building/storey_2_column_1",
      "http://example.org/building/storey_3_column_1",
      "http://example.org/building/storey_4_column_1",
      "http://example.org/building/storey_4_column_2",
      "http://example.org/building/storey_4_column_3",
      "http://example.org/building/storey_2_wall_1",
      "http://example.org/building/storey_2_wall_2",
      "http://example.org/building/storey_3_wall_1",
      "http://example.org/building/storey_3_wall_2",
      "http://example.org/building/storey_4_wall_1"
    ],
    "adjacency": [
      "http://example.org/building/floor_slab",
      "http://example.org/building/slab_1"
    ]
  },
  {
    "iri": "http://example.org/building/storey_2_column_1",
    "label": "Column",
    "serialization": {
      "rotation": 2.2,
      "location": "2.3915498370401846,-9.892253662659048,4.340706757864755",
      "size": "0.8619265476529576,0.6979337061703639,3.242012931671317"
    },
    "intersects": [],
    "isAbove": [
      "http://example.org/building/storey_1_column_1",
      "http://example.org/building/storey_1_column_2",
      "http://example.org/building/storey_1_wall_1",
      "http://example.org/building/storey_1_wall_2",
      "http://example.org/building/storey_1_wall_3"
    ],
    "isBelow": [
      "http://example.org/building/storey_3_column_1",
      "http://example.org/building/storey_4_column_1",
      "http://example.org/building/storey_4_column_2",
      "http://example.org/building/storey_4_column_3",
      "http://example.org/building/storey_3_wall_1",
      "http://example.org/building/storey_3_wall_2",
      "http://example.org/building/storey_4_wall_1"
    ],
    "adjacency": [
      "http://example.org/building/slab_1",
      "http://example.org/building/slab_2"
    ]
  },
  {
    "iri": "http://example.org/building/floor_slab",
    "label": "Floor Slab",
    "serialization": {
      "rotation": 0.0,
      "location": "4.006368713044006,4.587621808596412,0.0",
      "size": "6.67624605140977,13.318341934900516,0.30834983418219825"
    },
    "intersects": [
      "http://example.org/building/storey_1_column_1",
      "http://example.org/building/storey_1_column_2",
      "http://example.org/building/storey_1_wall_1",
      "http://example.org/building/storey_1_wall_2",
      "http://example.org/building/storey_1_wall_3"
    ],
    "isAbove": [],
    "isBelow": [
      "http://example.org/building/storey_2_column_1",
      "http://example.org/building/storey_3_column_1",
      "http://example.org/building/storey_4_column_1",
      "http://example.org/building/storey_4_column_2",
      "http://example.org/building/storey_4_column_3",
      "http://example.org/building/storey_2_wall_1",
      "http://example.org/building/storey_2_wall_2",
      "http://example.org/building/storey_3_wall_1",
      "http://example.org/building/storey_3_wall_2",
      "http://example.org/building/storey_4_wall_1"
    ],
    "adjacency": []
  },
  {
    "iri": "http://example.org/building/slab_1",
    "label": "Slab 1",
    "serialization": {
      "rotation": 0.0,
      "location": "3.7293839007655474,4.403372124795577,4.032356923682561",
      "size": "6.909681245586471,12.792006481791521,0.3083498341821995"
    },
    "intersects": [
      "http://example.org/building/storey_1_column_1",
      "http://example.org/building/storey_1_column_2",
      "http://example.org/building/storey_2_column_1",
      "http://example.org/building/storey_1_wall_1",
      "http://example.org/building/storey_1_wall_2",
      "http://example.org/building/storey_1_wall_3",
      "http://example.org/building/storey_2_wall_1",
      "http://example.org/building/storey_2_wall_2"
    ],
    "isAbove": [],
    "isBelow": [
      "http://example.org/building/storey_3_column_1",
      "http://example.org/building/storey_4_column_1",
      "http://example.org/building/storey_4_column_2",
      "http://example.org/building/storey_4_column_3",
      "http://example.org/building/storey_3_wall_1",
      "http://example.org/building/storey_3_wall_2",
      "http://example.org/building/storey_4_wall_1"
    ],
    "adjacency": []
  }
]