[
  {
    "iri": "http://example.org/building/storey_1_column_1",
    "label": "Column",
    "serialization": {
      "rotation": 0.0,
      "location": "5.870327811641297,2.7941991032923275,0.31380852197702974",
      "size": "0.35032538930196555,0.6182413188283356,2.978185236705034"
    },
    "intersects": [],
    "isAbove": [],
    "isBelow": [
      "http://example.org/building/storey_2_column_1",
      "http://example.org/building/storey_2_wall_1",
      "http://example.org/building/storey_2_wall_2",
      "http://example.org/building/storey_2_wall_3"
    ],
    "adjacency": [
      "http://example.org/building/floor_slab",
      "http://example.org/building/slab_1"
    ]
  },
  {
    "iri": "http://example.org/building/storey_1",
    "label": "Storey 1",
    "serialization": {
      "rotation": 1.3,
      "location": "2.8532756094848444,-10.434099275917955,0.0",
      "size": "16.532425107891076,8.567689349157392,3.291993758682066"
    },
    "intersects": [],
    "isAbove": [],
    "isBelow": [],
    "adjacency": []
  },
  {
    "iri": "http://example.org/building/roof_slab",
    "label": "Roof Slab",
    "serialization": {
      "rotation": 4.7,
      "location": "-14.742069092873017,2.967022204307428,8.82600409894965",
      "size": "11.01115179015428,8.729680142435305,0.31380852197703746"
    },
    "intersects": [
      "http://example.org/building/storey_2_column_1",
      "http://example.org/building/storey_2_wall_1",
      "http://example.org/building/storey_2_wall_2",
      "http://example.org/building/storey_2_wall_3"
    ],
    "isAbove": [
      "http://example.org/building/storey_1_column_1",
      "http://example.org/building/storey_1_column_2",
      "http://example.org/building/storey_1_column_3",
      "http://example.org/building/storey_1_column_4",
      "http://example.org/building/storey_1_wall_1",
      "http://example.org/building/storey_1_wall_2"
    ],
    "isBelow": [],
    "adjacency": []
  },
  {
    "iri": "http://example.org/building/storey_2_wall_2",
    "label": "Wall",
    "serialization": {
      "rotation": 6.0,
      "location": "3.580228050198466,6.845511760384429,3.6058022806590952",
      "size": "0.35134296019396727,6.0215570779595815,5.22020181829056"
    },
    "intersects": [],
    "isAbove": [
      "http://example.org/building/storey_1_column_1",
      "http://example.org/building/storey_1_column_2",
      "http://example.org/building/storey_1_column_3",
      "http://example.org/building/storey_1_column_4",
      "http://example.org/building/storey_1_wall_1",
      "http://example.org/building/storey_1_wall_2"
    ],
    "isBelow": [],
    "adjacency": [
      "http://example.org/building/slab_1",
      "http://example.org/building/roof_slab"
    ]
  },
  {
    "iri": "http://example.org/building/storey_1_column_2",
    "label": "Column",
    "serialization": {
      "rotation": 0.0,
      "location": "9.27288057909168,13.795580286254005,0.31380852197702974",
      "size": "0.3343878198254071,0.30965191559363703,2.978185236705034"
    },
    "intersects": [],
    "isAbove": [],
    "isBelow": [
      "http://example.org/building/storey_2_column_1",
      "http://example.org/building/storey_2_wall_1",
      "http://example.org/building/storey_2_wall_2",
      "http://example.org/building/storey_2_wall_3"
    ],
    "adjacency": [
      "http://example.org/building/floor_slab",
      "http://example.org/building/slab_1"
    ]
  },
  {
    "iri": "http://example.org/building/storey_1_column_3",
    "label": "Column",
    "serialization": {
      "rotation": 5.7,
      "location": "3.8003520922275777,11.5156740850904,0.3138085219770297",
      "size": "0.8400765757395048,0.6309847641768052,2.978185236705034"
    },
    "intersects": [
      "http://example.org/building/storey_1_wall_2"
    ],
    "isAbove": [],
    "isBelow": [
      "http://example.org/building/storey_2_column_1",
      "http://example.org/building/storey_2_wall_1",
      "http://example.org/building/storey_2_wall_2",
      "http://example.org/building/storey_2_wall_3"
    ],
    "adjacency": [
      "http://example.org/building/floor_slab",
      "http://example.org/building/slab_1"
    ]
  },
  {
    "iri": "http://example.org/building/storey_1_wall_1",
    "label": "Wall",
    "serialization": {
      "rotation": 3.0,
      "location": "-7.069854892557688,-10.775765002778883,0.31380852197702974",
      "size": "0.3156381573274043,5.143517840058819,2.9781852367050337"
    },
    "intersects": [],
    "isAbove": [],
    "isBelow": [
      "http://example.org/building/storey_2_column_1",
      "http://example.org/building/storey_2_wall_1",
      "http://example.org/building/storey_2_wall_2",
      "http://example.org/building/storey_2_wall_3"
    ],
    "adjacency": [
      "http://example.org/building/floor_slab",
      "http://example.org/building/slab_1"
    ]
  },
  {
    "iri": "http://example.org/building/storey_2_wall_3",
    "label": "Wall",
    "serialization": {
      "rotation": 3.3000000000000003,
      "location": "-11.522531931785949,-12.951666753277857,3.6058022806590952",
      "size": "0.41848535587270774,7.2586234017692775,5.22020181829056"
    },
    "intersects": [],
    "isAbove": [
      "http://example.org/building/storey_1_column_1",
      "http://example.org/building/storey_1_column_2",
      "http://example.org/building/storey_1_column_3",
      "http://example.org/building/storey_1_column_4",
      "http://example.org/building/storey_1_wall_1",
      "http://example.org/building/storey_1_wall_2"
    ],
    "isBelow": [],
    "adjacency": [
      "http://example.org/building/slab_1",
      "http://example.org/building/roof_slab"
    ]
  },
  {
    "iri": "http://example.org/building/storey_2_column_1",
    "label": "Column",
    "serialization": {
      "rotation": 5.5,
      "location": "1.9318314333689703,11.474359478588998,3.605802280659095",
      "size": "0.7894405379175278,0.7912312059585389,5.220201818290567"
    },
    "intersects": [],
    "isAbove": [
      "http://example.org/building/storey_1_column_1",
      "http://example.org/building/storey_1_column_2",
      "http://example.org/building/storey_1_column_3",
      "http://example.org/building/storey_1_column_4",
      "http://example.org/building/storey_1_wall_1",
      "http://example.org/building/storey_1_wall_2"
    ],
    "isBelow": [],
    "adjacency": [
      "http://example.org/building/slab_1",
      "http://example.org/building/roof_slab"
    ]
  },
  {
    "iri": "http://example.org/building/storey_1_column_4",
    "label": "Column",
    "serialization": {
      "rotation": 2.5,
      "location": "-4.131835386693764,-9.292836407602742,0.3138085219770297",
      "size": "0.9501835636982356,0.7856112929090227,2.978185236705034"
    },
    "intersects": [
      "http://example.org/building/storey_1_wall_2"
    ],
    "isAbove": [],
    "isBelow": [
      "http://example.org/building/storey_2_column_1",
      "http://example.org/building/storey_2_wall_1",
      "http://example.org/building/storey_2_wall_2",
      "http://example.org/building/storey_2_wall_3"
    ],
    "adjacency": [
      "http://example.org/building/floor_slab",
      "http://example.org/building/slab_1"
    ]
  },
  {
    "iri": "http://example.org/building/storey_1_wall_2",
    "label": "Wall",
    "serialization": {
      "rotation": 5.800000000000001,
      "location": "4.907058947328592,7.47994359665514,0.31380852197702974",
      "size": "0.25632668294959515,4.391232951524827,2.9781852367050337"
    },
    "intersects": [
      "http://example.org/building/storey_1_column_3",
      "http://example.org/building/storey_1_column_4"
    ],
    "isAbove": [],
    "isBelow": [
      "http://example.org/building/storey_2_column_1",
      "http://example.org/building/storey_2_wall_1",
      "http://example.org/building/storey_2_wall_2",
      "http://example.org/building/storey_2_wall_3"
    ],
    "adjacency": [
      "http://example.org/building/floor_slab",
      "http://example.org/building/slab_1"
    ]
  },
  {
    "iri": "http://example.org/building/building",
    "label": "Building",
    "serialization": {
      "rotation": 1.6,
      "location": "1.121967587081993,-13.930284293458834,0.0",
      "size": "15.404922910646466,10.353770801795307,8.826004098949657"
    },
    "intersects": [],
    "isAbove": [],
    "isBelow": [],
    "adjacency": []
  },
  {
    "iri": "http://example.org/building/storey_2",
    "label": "Storey 2",
    "serialization": {
      "rotation": 3.2,
      "location": "-13.687978594134997,-15.466266257841207,3.2919937586820636",
      "size": "9.759783152263172,13.729446040181532,5.534010340267593"
    },
    "intersects": [],
    "isAbove": [],
    "isBelow": [],
    "adjacency": []
  },
  {
    "iri": "http://example.org/building/floor_slab",
    "label": "Floor Slab",
    "serialization": {
      "rotation": 2.7,
      "location": "-8.634823740335529,-20.298967358015055,0.0",
      "size": "8.172603069654489,16.696847788859984,0.3138085219770298"
    },
    "intersects": [
      "http://example.org/building/storey_1_column_1",
      "http://example.org/building/storey_1_column_2",
      "http://example.org/building/storey_1_column_3",
      "http://example.org/building/storey_1_column_4",
      "http://example.org/building/storey_1_wall_1",
      "http://example.org/building/storey_1_wall_2"
    ],
    "isAbove": [],
    "isBelow": [
      "http://example.org/building/storey_2_column_1",
      "http://example.org/building/storey_2_wall_1",
      "http://example.org/building/storey_2_wall_2",
      "http://example.org/building/storey_2_wall_3"
    ],
    "adjacency": []
  },
  {
    "iri": "http://example.org/building/storey_2_wall_1",
    "label": "Wall",
    "serialization": {
      "rotation": 3.1,
      "location": "-7.861893203243527,-13.153349349399404,3.6058022806590952",
      "size": "0.27022477533762057,1.3185534046866696,5.22020181829056"
    },
    "intersects": [],
    "isAbove": [
      "http://example.org/building/storey_1_column_1",
      "http://example.org/building/storey_1_column_2",
      "http://example.org/building/storey_1_column_3",
      "http://example.org/building/storey_1_column_4",
      "http://example.org/building/storey_1_wall_1",
      "http://example.org/building/storey_1_wall_2"
    ],
    "isBelow": [],
    "adjacency": [
      "http://example.org/building/slab_1",
      "http://example.org/building/roof_slab"
    ]
  },
  {
    "iri": "http://example.org/building/slab_1",
    "label": "Slab 1",
    "serialization": {
      "rotation": 1.3,
      "location": "3.853410572103111,-9.737808645799861,3.291993758682065",
      "size": "14.246937745869086,7.871398719039298,0.31380852197703124"
    },
    "intersects": [
      "http://example.org/building/storey_1_column_1",
      "http://example.org/building/storey_1_column_2",
      "http://example.org/building/storey_1_column_3",
      "http://example.org/building/storey_1_column_4",
      "http://example.org/building/storey_2_column_1",
      "http://example.org/building/storey_1_wall_1",
      "http://example.org/building/storey_1_wall_2",
      "http://example.org/building/storey_2_wall_1",
      "http://example.org/building/storey_2_wall_2",
      "http://example.org/building/storey_2_wall_3"
    ],
    "isAbove": [],
    "isBelow": [],
    "adjacency": []
  }
]