[
  {
    "iri": "http://example.org/building/storey_1_column_1",
    "label": "Column",
    "serialization": {
      "rotation": 0.0,
      "location": "8.595527987195817,10.817489171897275,0.1689330594668641",
      "size": "0.35947793561796537,0.6338360195993733,3.4154811970266854"
    },
    "intersects": [],
    "isAbove": [],
    "isBelow": [
      "http://example.org/building/storey_2_column_1",
      "http://example.org/building/storey_2_column_2",
      "http://example.org/building/storey_2_column_3",
      "http://example.org/building/storey_3_column_1",
      "http://example.org/building/storey_3_column_2",
      "http://example.org/building/storey_4_column_1",
      "http://example.org/building/storey_5_column_1",
      "http://example.org/building/storey_5_column_2",
      "http://example.org/building/storey_2_wall_1",
      "http://example.org/building/storey_3_wall_1",
      "http://example.org/building/storey_4_wall_1",
      "http://example.org/building/storey_4_wall_2",
      "http://example.org/building/storey_5_wall_1",
      "http://example.org/building/storey_5_wall_2"
    ],
    "adjacency": [
      "http://example.org/building/floor_slab",
      "http://example.org/building/slab_1"
    ]
  },
  {
    "iri": "http://example.org/building/storey_3",
    "label": "Storey 3",
    "serialization": {
      "rotation": 6.1000000000000005,
      "location": "2.6030871710694603,3.926353455314582,7.484703222432126",
      "size": "10.99599767262551,10.365767423779692,3.66453911547835"
    },
    "intersects": [],
    "isAbove": [],
    "isBelow": [],
    "adjacency": []
  },
  {
    "iri": "http://example.org/building/storey_3_column_1",
    "label": "Column",
    "serialization": {
      "rotation": 3.9000000000000004,
      "location": "-9.465723405733172,-0.6986719410120132,7.65363628189899",
      "size": "0.6461771363850453,0.6274387914852274,3.4956060560114786"
    },
    "intersects": [],
    "isAbove": [
      "http://example.org/building/storey_1_column_1",
      "http://example.org/building/storey_1_column_2",
      "http://example.org/building/storey_2_column_1",
      "http://example.org/building/storey_2_column_2",
      "http://example.org/building/storey_2_column_3",
      "http://example.org/building/storey_1_wall_1",
      "http://example.org/building/storey_2_wall_1"
    ],
    "isBelow": [
      "http://example.org/building/storey_4_column_1",
      "http://example.org/building/storey_5_column_1",
      "http://example.org/building/storey_5_column_2",
      "http://example.org/building/storey_4_wall_1",
      "http://example.org/building/storey_4_wall_2",
      "http://example.org/building/storey_5_wall_1",
      "http://example.org/building/storey_5_wall_2"
    ],
    "adjacency": [
      "http://example.org/building/slab_2",
      "http://example.org/building/slab_3"
    ]
  },
  {
    "iri": "http://example.org/building/storey_5",
    "label": "Storey 5",
    "serialization": {
      "rotation": 2.3000000000000003,
      "location": "-6.958750450797213,-19.454826419265505,14.326761286628884",
      "size": "9.56343212146598,15.132795485227232,3.8536844710621487"
    },
    "intersects": [],
    "isAbove": [],
    "isBelow": [],
    "adjacency": []
  },
  {
    "iri": "http://example.org/building/building",
    "label": "Building",
    "serialization": {
      "rotation": 4.7,
      "location": "-13.05619576003048,3.035923125672266,0.0",
      "size": "11.634914775989255,13.820254660676213,18.180445757691032"
    },
    "intersects": [],
    "isAbove": [],
    "isBelow": [],
    "adjacency": []
  },
  {
    "iri": "http://example.org/building/storey_2",
    "label": "Storey 2",
    "serialization": {
      "rotation": 3.0,
      "location": "-13.251900755089679,-13.898685635581614,3.5844142564935497",
      "size": "10.535822923465192,9.491031335898196,3.9002889659385804"
    },
    "intersects": [],
    "isAbove": [],
    "isBelow": [],
    "adjacency": []
  },
  {
    "iri": "http://example.org/building/storey_4_wall_1",
    "label": "Wall",
    "serialization": {
      "rotation": 2.0,
      "location": "1.1200946566969288,-13.020907724058727,11.318175397377336",
      "size": "0.3513657141604125,5.224621260386295,3.008585889251547"
    },
    "intersects": [],
    "isAbove": [
      "http://example.org/building/storey_1_column_1",
      "http://example.org/building/storey_1_column_2",
      "http://example.org/building/storey_2_column_1",
      "http://example.org/building/storey_2_column_2",
      "http://example.org/building/storey_2_column_3",
      "http://example.org/building/storey_3_column_1",
      "http://example.org/building/storey_3_column_2",
      "http://example.org/building/storey_1_wall_1",
      "http://example.org/building/storey_2_wall_1",
      "http://example.org/building/storey_3_wall_1"
    ],
    "isBelow": [
      "http://example.org/building/storey_5_column_1",
      "http://example.org/building/storey_5_column_2",
      "http://example.org/building/storey_5_wall_1",
      "http://example.org/building/storey_5_wall_2"
    ],
    "adjacency": [
      "http://example.org/building/slab_3",
      "http://example.org/building/slab_4"
    ]
  },
  {
    "iri": "http://example.org/building/storey_3_wall_1",
    "label": "Wall",
    "serialization": {
      "rotation": 3.3000000000000003,
      "location": "-11.248518233322828,-6.639026361647792,7.653636281898994",
      "size": "0.17023790877379952,3.6401789396800126,3.4956060560114732"
    },
    "intersects": [],
    "isAbove": [
      "http://example.org/building/storey_1_column_1",
      "http://example.org/building/storey_1_column_2",
      "http://example.org/building/storey_2_column_1",
      "http://example.org/building/storey_2_column_2",
      "http://example.org/building/storey_2_column_3",
      "http://example.org/building/storey_1_wall_1",
      "http://example.org/building/storey_2_wall_1"
    ],
    "isBelow": [
      "http://example.org/building/storey_4_column_1",
      "http://example.org/building/storey_5_column_1",
      "http://example.org/building/storey_5_column_2",
      "http://example.org/building/storey_4_wall_1",
      "http://example.org/building/storey_4_wall_2",
      "http://example.org/building/storey_5_wall_1",
      "http://example.org/building/storey_5_wall_2"
    ],
    "adjacency": [
      "http://example.org/building/slab_2",
      "http://example.org/building/slab_3"
    ]
  },
  {
    "iri": "http://example.org/building/storey_4_wall_2",
    "label": "Wall",
    "serialization": {
      "rotation": 1.5,
      "location": "10.404734932972875,-11.901581625425544,11.318175397377336",
      "size": "0.2589563891203426,1.6523121375271028,3.008585889251547"
    },
    "intersects": [],
    "isAbove": [
      "http://example.org/building/storey_1_column_1",
      "http://example.org/building/storey_1_column_2",
      "http://example.org/building/storey_2_column_1",
      "http://example.org/building/storey_2_column_2",
      "http://example.org/building/storey_2_column_3",
      "http://example.org/building/storey_3_column_1",
      "http://example.org/building/storey_3_column_2",
      "http://example.org/building/storey_1_wall_1",
      "http://example.org/building/storey_2_wall_1",
      "http://example.org/building/storey_3_wall_1"
    ],
    "isBelow": [
      "http://example.org/building/storey_5_column_1",
      "http://example.org/building/storey_5_column_2",
      "http://example.org/building/storey_5_wall_1",
      "http://example.org/building/storey_5_wall_2"
    ],
    "adjacency": [
      "http://example.org/building/slab_3",
      "http://example.org/building/slab_4"
    ]
  },
  {
    "iri": "http://example.org/building/storey_4",
    "label": "Storey 4",
    "serialization": {
      "rotation": 5.800000000000001,
      "location": "0.5010602498012382,4.498530154115227,11.14924233791047",
      "size": "10.290958818343624,12.605957272017324,3.1775189487184203"
    },
    "intersects": [],
    "isAbove": [],
    "isBelow": [],
    "adjacency": []
  },
  {
    "iri": "http://example.org/building/roof_slab",
    "label": "Roof Slab",
    "serialization": {
      "rotation": 3.7,
      "location": "-19.62319780630667,-3.7801913554454503,18.180445757691025",
      "size": "15.283425225718956,8.44252228810696,0.1689330594668661"
    },
    "intersects": [
      "http://example.org/building/storey_5_column_1",
      "http://example.org/building/storey_5_column_2",
      "http://example.org/building/storey_5_wall_1",
      "http://example.org/building/storey_5_wall_2"
    ],
    "isAbove": [
      "http://example.org/building/storey_1_column_1",
      "http://example.org/building/storey_1_column_2",
      "http://example.org/building/storey_2_column_1",
      "http://example.org/building/storey_2_column_2",
      "http://example.org/building/storey_2_column_3",
      "http://example.org/building/storey_3_column_1",
      "http://example.org/building/storey_3_column_2",
      "http://example.org/building/storey_4_column_1",
      "http://example.org/building/storey_1_wall_1",
      "http://example.org/building/storey_2_wall_1",
      "http://example.org/building/storey_3_wall_1",
      "http://example.org/building/storey_4_wall_1",
      "http://example.org/building/storey_4_wall_2"
    ],
    "isBelow": [],
    "adjacency": []
  },
  {
    "iri": "http://example.org/building/storey_5_wall_2",
    "label": "Wall",
    "serialization": {
      "rotation": 1.9000000000000001,
      "location": "3.374068062728719,-16.315082482436978,14.495694346095746",
      "size": "0.2546153175133674,9.29878081455653,3.684751411595279"
    },
    "intersects": [],
    "isAbove": [
      "http://example.org/building/storey_1_column_1",
      "http://example.org/building/storey_1_column_2",
      "http://example.org/building/storey_2_column_1",
      "http://example.org/building/storey_2_column_2",
      "http://example.org/building/storey_2_column_3",
      "http://example.org/building/storey_3_column_1",
      "http://example.org/building/storey_3_column_2",
      "http://example.org/building/storey_4_column_1",
      "http://example.org/building/storey_1_wall_1",
      "http://example.org/building/storey_2_wall_1",
      "http://example.org/building/storey_3_wall_1",
      "http://example.org/building/storey_4_wall_1",
      "http://example.org/building/storey_4_wall_2"
    ],
    "isBelow": [],
    "adjacency": [
      "http://example.org/building/slab_4",
      "http://example.org/building/roof_slab"
    ]
  },
  {
    "iri": "http://example.org/building/storey_1",
    "label": "Storey 1",
    "serialization": {
      "rotation": 3.1,
      "location": "-13.599687048380185,-13.166875900035507,0.0",
      "size": "10.946293110359932,8.97171098803945,3.5844142564935524"
    },
    "intersects": [],
    "isAbove": [],
    "isBelow": [],
    "adjacency": []
  },
  {
    "iri": "http://example.org/building/storey_2_wall_1",
    "label": "Wall",
    "serialization": {
      "rotation": 2.0,
      "location": "0.4500964861007999,-11.97472038362447,3.753347315960416",
      "size": "1.2410969425143374,0.2666998687710844,3.73135590647171"
    },
    "intersects": [],
    "isAbove": [
      "http://example.org/building/storey_1_column_1",
      "http://example.org/building/storey_1_column_2",
      "http://example.org/building/storey_1_wall_1"
    ],
    "isBelow": [
      "http://example.org/building/storey_3_column_1",
      "http://example.org/building/storey_3_column_2",
      "http://example.org/building/storey_4_column_1",
      "http://example.org/building/storey_5_column_1",
      "http://example.org/building/storey_5_column_2",
      "http://example.org/building/storey_3_wall_1",
      "http://example.org/building/storey_4_wall_1",
      "http://example.org/building/storey_4_wall_2",
      "http://example.org/building/storey_5_wall_1",
      "http://example.org/building/storey_5_wall_2"
    ],
    "adjacency": [
      "http://example.org/building/slab_1",
      "http://example.org/building/slab_2"
    ]
  },
  {
    "iri": "http://example.org/building/storey_5_wall_1",
    "label": "Wall",
    "serialization": {
      "rotation": 5.9,
      "location": "4.200656301932758,5.532453361123036,14.495694346095746",
      "size": "0.31922850378862844,0.3921793228280004,3.684751411595279"
    },
    "intersects": [],
    "isAbove": [
      "http://example.org/building/storey_1_column_1",
      "http://example.org/building/storey_1_column_2",
      "http://example.org/building/storey_2_column_1",
      "http://example.org/building/storey_2_column_2",
      "http://example.org/building/storey_2_column_3",
      "http://example.org/building/storey_3_column_1",
      "http://example.org/building/storey_3_column_2",
      "http://example.org/building/storey_4_column_1",
      "http://example.org/building/storey_1_wall_1",
      "http://example.org/building/storey_2_wall_1",
      "http://example.org/building/storey_3_wall_1",
      "http://example.org/building/storey_4_wall_1",
      "http://example.org/building/storey_4_wall_2"
    ],
    "isBelow": [],
    "adjacency": [
      "http://example.org/building/slab_4",
      "http://example.org/building/roof_slab"
    ]
  },
  {
    "iri": "http://example.org/building/storey_2_column_2",
    "label": "Column",
    "serialization": {
      "rotation": 2.3000000000000003,
      "location": "-1.394638864793361,-9.821642210098815,3.7533473159604127",
      "size": "0.892899077913138,0.9520818653947316,3.731355906471713"
    },
    "intersects": [],
    "isAbove": [
      "http://example.org/building/storey_1_column_1",
      "http://example.org/building/storey_1_column_2",
      "http://example.org/building/storey_1_wall_1"
    ],
    "isBelow": [
      "http://example.org/building/storey_3_column_1",
      "http://example.org/building/storey_3_column_2",
      "http://example.org/building/storey_4_column_1",
      "http://example.org/building/storey_5_column_1",
      "http://example.org/building/storey_5_column_2",
      "http://example.org/building/storey_3_wall_1",
      "http://example.org/building/storey_4_wall_1",
      "http://example.org/building/storey_4_wall_2",
      "http://example.org/building/storey_5_wall_1",
      "http://example.org/building/storey_5_wall_2"
    ],
    "adjacency": [
      "http://example.org/building/slab_1",
      "http://example.org/building/slab_2"
    ]
  },
  {
    "iri": "http://example.org/building/storey_4_column_1",
    "label": "Column",
    "serialization": {
      "rotation": 4.1000000000000005,
      "location": "-12.612119992552369,0.335282682835226,11.318175397377335",
      "size": "0.6726898006110353,0.8529094109896835,3.008585889251549"
    },
    "intersects": [],
    "isAbove": [
      "http://example.org/building/storey_1_column_1",
      "http://example.org/building/storey_1_column_2",
      "http://example.org/building/storey_2_column_1",
      "http://example.org/building/storey_2_column_2",
      "http://example.org/building/storey_2_column_3",
      "http://example.org/building/storey_3_column_1",
      "http://example.org/building/storey_3_column_2",
      "http://example.org/building/storey_1_wall_1",
      "http://example.org/building/storey_2_wall_1",
      "http://example.org/building/storey_3_wall_1"
    ],
    "isBelow": [
      "http://example.org/building/storey_5_column_1",
      "http://example.org/building/storey_5_column_2",
      "http://example.org/building/storey_5_wall_1",
      "http://example.org/building/storey_5_wall_2"
    ],
    "adjacency": [
      "http://example.org/building/slab_3",
      "http://example.org/building/slab_4"
    ]
  },
  {
    "iri": "http://example.org/building/slab_3",
    "label": "Slab 3",
    "serialization": {
      "rotation": 4.3,
      "location": "-16.309673862160842,1.0804037733052612,11.149242337910472",
      "size": "11.374435472243835,9.864346955542409,0.16893305946686965"
    },
    "intersects": [
      "http://example.org/building/storey_3_column_1",
      "http://example.org/building/storey_3_column_2",
      "http://example.org/building/storey_4_column_1",
      "http://example.org/building/storey_3_wall_1",
      "http://example.org/building/storey_4_wall_1",
      "http://example.org/building/storey_4_wall_2"
    ],
    "isAbove": [
      "http://example.org/building/storey_1_column_1",
      "http://example.org/building/storey_1_column_2",
      "http://example.org/building/storey_2_column_1",
      "http://example.org/building/storey_2_column_2",
      "http://example.org/building/storey_2_column_3",
      "http://example.org/building/storey_1_wall_1",
      "http://example.org/building/storey_2_wall_1"
    ],
    "isBelow": [
      "http://example.org/building/storey_5_column_1",
      "http://example.org/building/storey_5_column_2",
      "http://example.org/building/storey_5_wall_1",
      "http://example.org/building/storey_5_wall_2"
    ],
    "adjacency": []
  },
  {
    "iri": "http://example.org/building/storey_1_wall_1",
    "label": "Wall",
    "serialization": {
      "rotation": 1.1,
      "location": "12.366304435451866,-6.3601896313689235,0.1689330594668641",
      "size": "0.17384327501308583,2.734978073274857,3.4154811970266854"
    },
    "intersects": [],
    "isAbove": [],
    "isBelow": [
      "http://example.org/building/storey_2_column_1",
      "http://example.org/building/storey_2_column_2",
      "http://example.org/building/storey_2_column_3",
      "http://example.org/building/storey_3_column_1",
      "http://example.org/building/storey_3_column_2",
      "http://example.org/building/storey_4_column_1",
      "http://example.org/building/storey_5_column_1",
      "http://example.org/building/storey_5_column_2",
      "http://example.org/building/storey_2_wall_1",
      "http://example.org/building/storey_3_wall_1",
      "http://example.org/building/storey_4_wall_1",
      "http://example.org/building/storey_4_wall_2",
      "http://example.org/building/storey_5_wall_1",
      "http://example.org/building/storey_5_wall_2"
    ],
    "adjacency": [
      "http://example.org/building/floor_slab",
      "http://example.org/building/slab_1"
    ]
  },
  {
    "iri": "http://example.org/building/storey_3_column_2",
    "label": "Column",
    "serialization": {
      "rotation": 5.6000000000000005,
      "location": "1.7355268361010223,13.030176826236291,7.65363628189899",
      "size": "0.8815026009532527,0.7774121367770217,3.4956060560114786"
    },
    "intersects": [],
    "isAbove": [
      "http://example.org/building/storey_1_column_1",
      "http://example.org/building/storey_1_column_2",
      "http://example.org/building/storey_2_column_1",
      "http://example.org/building/storey_2_column_2",
      "http://example.org/building/storey_2_column_3",
      "http://example.org/building/storey_1_wall_1",
      "http://example.org/building/storey_2_wall_1"
    ],
    "isBelow": [
      "http://example.org/building/storey_4_column_1",
      "http://example.org/building/storey_5_column_1",
      "http://example.org/building/storey_5_column_2",
      "http://example.org/building/storey_4_wall_1",
      "http://example.org/building/storey_4_wall_2",
      "http://example.org/building/storey_5_wall_1",
      "http://example.org/building/storey_5_wall_2"
    ],
    "adjacency": [
      "http://example.org/building/slab_2",
      "http://example.org/building/slab_3"
    ]
  },
  {
    "iri": "http://example.org/building/slab_2",
    "label": "Slab 2",
    "serialization": {
      "rotation": 2.9000000000000004,
      "location": "-12.119715185450918,-14.755874765758673,7.484703222432128",
      "size": "9.943956230135196,9.752477524321076,0.16893305946686787"
    },
    "intersects": [
      "http://example.org/building/storey_2_column_1",
      "http://example.org/building/storey_2_column_2",
      "http://example.org/building/storey_2_column_3",
      "http://example.org/building/storey_3_column_1",
      "http://example.org/building/storey_3_column_2",
      "http://example.org/building/storey_2_wall_1",
      "http://example.org/building/storey_3_wall_1"
    ],
    "isAbove": [
      "http://example.org/building/storey_1_column_1",
      "http://example.org/building/storey_1_column_2",
      "http://example.org/building/storey_1_wall_1"
    ],
    "isBelow": [
      "http://example.org/building/storey_4_column_1",
      "http://example.org/building/storey_5_column_1",
      "http://example.org/building/storey_5_column_2",
      "http://example.org/building/storey_4_wall_1",
      "http://example.org/building/storey_4_wall_2",
      "http://example.org/building/storey_5_wall_1",
      "http://example.org/building/storey_5_wall_2"
    ],
    "adjacency": []
  },
  {
    "iri": "http://example.org/building/storey_1_column_2",
    "label": "Column",
    "serialization": {
      "rotation": 3.9000000000000004,
      "location": "-10.830189996914712,-0.27040574128375294,0.16893305946686402",
      "size": "0.946954356269595,0.974505976100935,3.415481197026686"
    },
    "intersects": [],
    "isAbove": [],
    "isBelow": [
      "http://example.org/building/storey_2_column_1",
      "http://example.org/building/storey_2_column_2",
      "http://example.org/building/storey_2_column_3",
      "http://example.org/building/storey_3_column_1",
      "http://example.org/building/storey_3_column_2",
      "http://example.org/building/storey_4_column_1",
      "http://example.org/building/storey_5_column_1",
      "http://example.org/building/storey_5_column_2",
      "http://example.org/building/storey_2_wall_1",
      "http://example.org/building/storey_3_wall_1",
      "http://example.org/building/storey_4_wall_1",
      "http://example.org/building/storey_4_wall_2",
      "http://example.org/building/storey_5_wall_1",
      "http://example.org/building/storey_5_wall_2"
    ],
    "adjacency": [
      "http://example.org/building/floor_slab",
      "http://example.org/building/slab_1"
    ]
  },
  {
    "iri": "http://example.org/building/storey_2_column_3",
    "label": "Column",
    "serialization": {
      "rotation": 3.9000000000000004,
      "location": "-11.399850951000982,-2.3290714456434225,3.7533473159604127",
      "size": "0.7178908563437147,0.6972826535661356,3.731355906471713"
    },
    "intersects": [],
    "isAbove": [
      "http://example.org/building/storey_1_column_1",
      "http://example.org/building/storey_1_column_2",
      "http://example.org/building/storey_1_wall_1"
    ],
    "isBelow": [
      "http://example.org/building/storey_3_column_1",
      "http://example.org/building/storey_3_column_2",
      "http://example.org/building/storey_4_column_1",
      "http://example.org/building/storey_5_column_1",
      "http://example.org/building/storey_5_column_2",
      "http://example.org/building/storey_3_wall_1",
      "http://example.org/building/storey_4_wall_1",
      "http://example.org/building/storey_4_wall_2",
      "http://example.org/building/storey_5_wall_1",
      "http://example.org/building/storey_5_wall_2"
    ],
    "adjacency": [
      "http://example.org/building/slab_1",
      "http://example.org/building/slab_2"
    ]
  },
  {
    "iri": "http://example.org/building/floor_slab",
    "label": "Floor Slab",
    "serialization": {
      "rotation": 3.1,
      "location": "-12.871215965604524,-13.166875900035508,0.0",
      "size": "10.21782202758427,8.536449150387178,0.16893305946686413"
    },
    "intersects": [
      "http://example.org/building/storey_1_column_1",
      "http://example.org/building/storey_1_column_2",
      "http://example.org/building/storey_1_wall_1"
    ],
    "isAbove": [],
    "isBelow": [
      "http://example.org/building/storey_2_column_1",
      "http://example.org/building/storey_2_column_2",
      "http://example.org/building/storey_2_column_3",
      "http://example.org/building/storey_3_column_1",
      "http://example.org/building/storey_3_column_2",
      "http://example.org/building/storey_4_column_1",
      "http://example.org/building/storey_5_column_1",
      "http://example.org/building/storey_5_column_2",
      "http://example.org/building/storey_2_wall_1",
      "http://example.org/building/storey_3_wall_1",
      "http://example.org/building/storey_4_wall_1",
      "http://example.org/building/storey_4_wall_2",
      "http://example.org/building/storey_5_wall_1",
      "http://example.org/building/storey_5_wall_2"
    ],
    "adjacency": []
  },
  {
    "iri": "http://example.org/building/slab_4",
    "label": "Slab 4",
    "serialization": {
      "rotation": 0.8,
      "location": "4.956526659885757,-7.149592157026769,14.326761286628882",
      "size": "13.665792577562694,8.92598859557043,0.16893305946687143"
    },
    "intersects": [
      "http://example.org/building/storey_4_column_1",
      "http://example.org/building/storey_5_column_1",
      "http://example.org/building/storey_5_column_2",
      "http://example.org/building/storey_4_wall_1",
      "http://example.org/building/storey_4_wall_2",
      "http://example.org/building/storey_5_wall_1",
      "http://example.org/building/storey_5_wall_2"
    ],
    "isAbove": [
      "http://example.org/building/storey_1_column_1",
      "http://example.org/building/storey_1_column_2",
      "http://example.org/building/storey_2_column_1",
      "http://example.org/building/storey_2_column_2",
      "http://example.org/building/storey_2_column_3",
      "http://example.org/building/storey_3_column_1",
      "http://example.org/building/storey_3_column_2",
      "http://example.org/building/storey_1_wall_1",
      "http://example.org/building/storey_2_wall_1",
      "http://example.org/building/storey_3_wall_1"
    ],
    "isBelow": [],
    "adjacency": []
  },
  {
    "iri": "http://example.org/building/storey_2_column_1",
    "label": "Column",
    "serialization": {
      "rotation": 0.8,
      "location": "11.82132311047636,2.3812099740901376,3.7533473159604127",
      "size": "0.6374231507465922,0.6472587506123215,3.731355906471713"
    },
    "intersects": [],
    "isAbove": [
      "http://example.org/building/storey_1_column_1",
      "http://example.org/building/storey_1_column_2",
      "http://example.org/building/storey_1_wall_1"
    ],
    "isBelow": [
      "http://example.org/building/storey_3_column_1",
      "http://example.org/building/storey_3_column_2",
      "http://example.org/building/storey_4_column_1",
      "http://example.org/building/storey_5_column_1",
      "http://example.org/building/storey_5_column_2",
      "http://example.org/building/storey_3_wall_1",
      "http://example.org/building/storey_4_wall_1",
      "http://example.org/building/storey_4_wall_2",
      "http://example.org/building/storey_5_wall_1",
      "http://example.org/building/storey_5_wall_2"
    ],
    "adjacency": [
      "http://example.org/building/slab_1",
      "http://example.org/building/slab_2"
    ]
  },
  {
    "iri": "http://example.org/building/storey_5_column_1",
    "label": "Column",
    "serialization": {
      "rotation": 3.9000000000000004,
      "location": "-12.198938195072488,4.089772378451297,14.495694346095743",
      "size": "0.7438048001074744,0.766061276568891,3.6847514115952826"
    },
    "intersects": [],
    "isAbove": [
      "http://example.org/building/storey_1_column_1",
      "http://example.org/building/storey_1_column_2",
      "http://example.org/building/storey_2_column_1",
      "http://example.org/building/storey_2_column_2",
      "http://example.org/building/storey_2_column_3",
      "http://example.org/building/storey_3_column_1",
      "http://example.org/building/storey_3_column_2",
      "http://example.org/building/storey_4_column_1",
      "http://example.org/building/storey_1_wall_1",
      "http://example.org/building/storey_2_wall_1",
      "http://example.org/building/storey_3_wall_1",
      "http://example.org/building/storey_4_wall_1",
      "http://example.org/building/storey_4_wall_2"
    ],
    "isBelow": [],
    "adjacency": [
      "http://example.org/building/slab_4",
      "http://example.org/building/roof_slab"
    ]
  },
  {
    "iri": "http://example.org/building/storey_5_column_2",
    "label": "Column",
    "serialization": {
      "rotation": 0.0,
      "location": "10.22708616238019,8.794689335897562,14.495694346095746",
      "size": "0.6733377602898791,0.42554494198439485,3.684751411595279"
    },
    "intersects": [],
    "isAbove": [
      "http://example.org/building/storey_1_column_1",
      "http://example.org/building/storey_1_column_2",
      "http://example.org/building/storey_2_column_1",
      "http://example.org/building/storey_2_column_2",
      "http://example.org/building/storey_2_column_3",
      "http://example.org/building/storey_3_column_1",
      "http://example.org/building/storey_3_column_2",
      "http://example.org/building/storey_4_column_1",
      "http://example.org/building/storey_1_wall_1",
      "http://example.org/building/storey_2_wall_1",
      "http://example.org/building/storey_3_wall_1",
      "http://example.org/building/storey_4_wall_1",
      "http://example.org/building/storey_4_wall_2"
    ],
    "isBelow": [],
    "adjacency": [
      "http://example.org/building/slab_4",
      "http://example.org/building/roof_slab"
    ]
  },
  {
    "iri": "http://example.org/building/slab_1",
    "label": "Slab 1",
    "serialization": {
      "rotation": 3.0,
      "location": "-12.409745014625408,-13.898685635581622,3.5844142564935515",
      "size": "9.693667183000919,8.705146507101897,0.16893305946686477"
    },
    "intersects": [
      "http://example.org/building/storey_1_column_1",
      "http://example.org/building/storey_1_column_2",
      "http://example.org/building/storey_2_column_1",
      "http://example.org/building/storey_2_column_2",
      "http://example.org/building/storey_2_column_3",
      "http://example.org/building/storey_1_wall_1",
      "http://example.org/building/storey_2_wall_1"
    ],
    "isAbove": [],
    "isBelow": [
      "http://example.org/building/storey_3_column_1",
      "http://example.org/building/storey_3_column_2",
      "http://example.org/building/storey_4_column_1",
      "http://example.org/building/storey_5_column_1",
      "http://example.org/building/storey_5_column_2",
      "http://example.org/building/storey_3_wall_1",
      "http://example.org/building/storey_4_wall_1",
      "http://example.org/building/storey_4_wall_2",
      "http://example.org/building/storey_5_wall_1",
      "http://example.org/building/storey_5_wall_2"
    ],
    "adjacency": []
  }
]